LICENSE
README.md
setup.py
iRabbitPro/__init__.py
iRabbitPro/api.py
iRabbitPro/irabbit.py
iRabbitPro/proxy.py
iRabbitPro/tempCodeRunnerFile.py
iRabbitPro.egg-info/PKG-INFO
iRabbitPro.egg-info/SOURCES.txt
iRabbitPro.egg-info/dependency_links.txt
iRabbitPro.egg-info/requires.txt
iRabbitPro.egg-info/top_level.txt