Metadata-Version: 2.1
Name: iRabbitPro
Version: 93.0.0
Summary: a automated post tools
Home-page: https://github.com/irabbit666/iRabbitPro
Author: iRabbit
Author-email: 8381595@qq.com
License: UNKNOWN
Platform: UNKNOWN
License-File: LICENSE
